commacalc/__init__.py
commacalc/currencies.py
commacalc/extra.py
commacalc/pretty_number.py
commacalc/primes.py
commacalc/units.py
"usr/share/bash-completion/completions/,"
commacalc-4.2.2.dist-info/LICENCE
commacalc-4.2.2.dist-info/METADATA
commacalc-4.2.2.dist-info/WHEEL
commacalc-4.2.2.dist-info/entry_points.txt
commacalc-4.2.2.dist-info/top_level.txt
commacalc-4.2.2.dist-info/RECORD
