Metadata-Version: 2.1
Name: commacalc
Version: 4.2.2
Summary: Command line calc
Home-page: https://gitlab.com/pacholik1/CommaCalc
Author: Vojtěch Pachol
Author-email: pacholick@gmail.com
License: LGPL-3.0
Keywords: python,math,calc
Platform: UNKNOWN
Classifier: Development Status :: 5 - Production/Stable
Classifier: Programming Language :: Python :: 3
License-File: LICENCE
Requires-Dist: colorama
Requires-Dist: httplib2
